pyloadart/__init__.py
pyloadart/base_.py
pyloadart/loop.py
pyloadart-0.0.1.dist-info/LICENSE
pyloadart-0.0.1.dist-info/METADATA
pyloadart-0.0.1.dist-info/WHEEL
pyloadart-0.0.1.dist-info/top_level.txt
pyloadart-0.0.1.dist-info/RECORD
