Metadata-Version: 2.1
Name: pyloadart
Version: 0.0.1
Summary: It displays loading like structure in loopy statement
Home-page: https://github.com/Madhava-mng/pyloadart
Author: Madhava-mng
Author-email: alformint@gmail.com
License: UNKNOWN
Platform: UNKNOWN
Classifier: Programming Language :: Python :: 3
Classifier: License :: OSI Approved :: MIT License
Classifier: Operating System :: OS Independent
Requires-Python: >=3.6
